<?xml version="1.0" standalone="yes"?>

<extension name="Hello World" version="0.1" >
  <author>Timothy Fish</author>
  <date>July 2011</date>

  <plugin class="extending.aoi.hello.FirstPlugin" />

  <description>First project for extending Art of Illusion</description>

  <comments>This is an example of a very simple project for Art of Illusion.</comments>

  <history>
     <log version="0.1" date="July 2011" author="Timothy Fish" >- Initial Version</log>
  </history>

</extension>